rubiJeff/An_Wb.py
rubiJeff/How.py
rubiJeff/Socket.py
rubiJeff/__init__.py
rubiJeff/client.py
rubiJeff/encryption.py
rubiJeff-1.1.2.dist-info/LICENCE
rubiJeff-1.1.2.dist-info/METADATA
rubiJeff-1.1.2.dist-info/WHEEL
rubiJeff-1.1.2.dist-info/top_level.txt
rubiJeff-1.1.2.dist-info/RECORD
